safa_sdk/__init__.py
safa_sdk/constants.py
safa_sdk/http_client.py
safa_sdk/safa_client.py
safa_sdk/safa_store.py
safa_sdk/util.py
safa_sdk-0.1.6.dist-info/METADATA
safa_sdk-0.1.6.dist-info/WHEEL
safa_sdk-0.1.6.dist-info/licenses/LICENSE
safa_sdk-0.1.6.dist-info/RECORD
