Metadata-Version: 2.3
Name: safa-sdk
Version: 0.1.6
Summary: A Python SDK wrapper for a SAFA REST API.
Project-URL: Homepage, https://github.com/nd-safa/safa-sdk-python
Author-email: Alberto Rodriguez <alberto@safa.ai.com>
License: MIT
License-File: LICENSE
Requires-Python: >=3.10
Requires-Dist: certifi==2024.6.2
Requires-Dist: charset-normalizer==3.3.2
Requires-Dist: idna==3.7
Requires-Dist: python-dotenv==1.0.1
Requires-Dist: requests==2.32.3
Requires-Dist: urllib3==2.2.2
